BWS/__init__.py
BWS/utils.py
BWS/api/__init__.py
BWS/api/api.py
BWS/api/api_company_details.py
BWS/api/api_part2.py
BWS/api/api_part3.py
BWS/api/api_update.py
BWS/api/main.py
BWS/database/__init__.py
BWS/database/db_interactions.py
BWS/database/sqlite.py
BWS/logger/__init__.py
BWS/logger/logger.py
BWS/model/__init__.py
BWS/model/analysis.py
myBWS-0.1.1.dist-info/LICENSE
myBWS-0.1.1.dist-info/METADATA
myBWS-0.1.1.dist-info/WHEEL
myBWS-0.1.1.dist-info/top_level.txt
myBWS-0.1.1.dist-info/RECORD
