Metadata-Version: 2.1
Name: myBWS
Version: 0.1.1
Summary: Tool for conducting and analyzing best-worst scaling surveys
Author: Aram Barseghyan, Sergo Poghosyan, Arevik Papikyan, Nare Stepanyan, Elen Sukiasyan
Classifier: Development Status :: 3 - Alpha
Requires-Python: >=3.10, <3.12
License-File: LICENSE
Requires-Dist: annotated-types ==0.6.0
Requires-Dist: anyio ==4.3.0
Requires-Dist: Babel ==2.14.0
Requires-Dist: backports.tarfile ==1.0.0
Requires-Dist: build ==1.2.1
Requires-Dist: certifi ==2024.2.2
Requires-Dist: charset-normalizer ==3.3.2
Requires-Dist: click ==8.1.7
Requires-Dist: colorama ==0.4.6
Requires-Dist: docutils ==0.21
Requires-Dist: fastapi ==0.110.0
Requires-Dist: ghp-import ==2.1.0
Requires-Dist: h11 ==0.14.0
Requires-Dist: idna ==3.6
Requires-Dist: importlib-metadata ==7.1.0
Requires-Dist: jaraco.classes ==3.4.0
Requires-Dist: jaraco.context ==5.3.0
Requires-Dist: jaraco.functools ==4.0.0
Requires-Dist: Jinja2 ==3.1.3
Requires-Dist: keyring ==25.1.0
Requires-Dist: Markdown ==3.6
Requires-Dist: markdown-it-py ==3.0.0
Requires-Dist: MarkupSafe ==2.1.5
Requires-Dist: mdurl ==0.1.2
Requires-Dist: mergedeep ==1.3.4
Requires-Dist: more-itertools ==10.2.0
Requires-Dist: nh3 ==0.2.17
Requires-Dist: numpy ==1.26.4
Requires-Dist: packaging ==24.0
Requires-Dist: paginate ==0.5.6
Requires-Dist: pandas ==2.2.1
Requires-Dist: pathspec ==0.12.1
Requires-Dist: pkginfo ==1.10.0
Requires-Dist: platformdirs ==4.2.0
Requires-Dist: pydantic ==2.6.4
Requires-Dist: pydantic-core ==2.16.3
Requires-Dist: Pygments ==2.17.2
Requires-Dist: pymdown-extensions ==10.8
Requires-Dist: pyproject-hooks ==1.0.0
Requires-Dist: pyreadr ==0.5.0
Requires-Dist: python-dateutil ==2.9.0.post0
Requires-Dist: pytz ==2024.1
Requires-Dist: pywin32-ctypes ==0.2.2
Requires-Dist: PyYAML ==6.0.1
Requires-Dist: pyyaml-env-tag ==0.1
Requires-Dist: readme-renderer ==43.0
Requires-Dist: regex ==2024.4.16
Requires-Dist: requests ==2.31.0
Requires-Dist: requests-toolbelt ==1.0.0
Requires-Dist: rfc3986 ==2.0.0
Requires-Dist: rich ==13.7.1
Requires-Dist: scipy ==1.13.0
Requires-Dist: six ==1.16.0
Requires-Dist: sniffio ==1.3.1
Requires-Dist: starlette ==0.36.3
Requires-Dist: twine ==5.0.0
Requires-Dist: typing ==3.7.4.3
Requires-Dist: tzdata ==2024.1
Requires-Dist: urllib3 ==2.2.1
Requires-Dist: uvicorn ==0.29.0
Requires-Dist: watchdog ==4.0.0
Requires-Dist: zipp ==3.18.1
